docker_release/__init__.py
docker_release/docker_release.py
docker_release/main.py
docker_release-0.8.dist-info/DESCRIPTION.rst
docker_release-0.8.dist-info/METADATA
docker_release-0.8.dist-info/RECORD
docker_release-0.8.dist-info/WHEEL
docker_release-0.8.dist-info/entry_points.txt
docker_release-0.8.dist-info/metadata.json
docker_release-0.8.dist-info/top_level.txt
