Metadata-Version: 2.0
Name: docker-release
Version: 0.8
Summary: 
Requires-Dist: GitPython (==1.0.1)
Requires-Dist: docker-py (>=1.7.0)
Requires-Dist: requests (==2.7.0)
